__init__.py
video_compress.py
batch_compress_video_cli-0.2.1.dist-info/LICENSE.txt
batch_compress_video_cli-0.2.1.dist-info/METADATA
batch_compress_video_cli-0.2.1.dist-info/WHEEL
batch_compress_video_cli-0.2.1.dist-info/entry_points.txt
batch_compress_video_cli-0.2.1.dist-info/top_level.txt
batch_compress_video_cli-0.2.1.dist-info/RECORD
