Metadata-Version: 2.1
Name: batch-compress-video-cli
Version: 0.2.1
Summary: Compress raw video from action cameras from directory or path using ffmpeg, with a simple cli to automate the recurring commands.
Author-email: Rocky Li <aperocky@gmail.com>
License: MIT License
Project-URL: Homepage, https://github.com/Aperocky/batch-compress-video-cli
Project-URL: Source, https://github.com/Aperocky/batch-compress-video-cli
Keywords: ffmpeg,compress,video,batch,cli
License-File: LICENSE.txt
Requires-Dist: ffmpeg-python
Provides-Extra: test
Requires-Dist: pytest ; extra == 'test'
Requires-Dist: coverage ; extra == 'test'
